fractal/matrix/__init__.py
fractal/matrix/async_client.py
fractal/matrix/controllers/__init__.py
fractal/matrix/exceptions.py
fractal/matrix/utils.py
fractal_matrix_client-0.0.8.dist-info/LICENSE
fractal_matrix_client-0.0.8.dist-info/METADATA
fractal_matrix_client-0.0.8.dist-info/WHEEL
fractal_matrix_client-0.0.8.dist-info/RECORD
