Metadata-Version: 2.1
Name: fractal-matrix-client
Version: 0.0.8
Summary: 
Author: Mo Balaa
Author-email: balaa@fractalnetworks.co
Requires-Python: >=3.10,<4.0
Classifier: Programming Language :: Python :: 3
Classifier: Programming Language :: Python :: 3.10
Classifier: Programming Language :: Python :: 3.11
Classifier: Programming Language :: Python :: 3.12
Provides-Extra: dev
Requires-Dist: PyYAML (>=6.0.1,<7.0.0)
Requires-Dist: aiofiles (>=23.1.0,<24.0.0)
Requires-Dist: aioresponses (>=0.7.6,<0.8.0) ; extra == "dev"
Requires-Dist: appdirs (>=1.4.4,<2.0.0)
Requires-Dist: docker (>=7.1.0,<8.0.0)
Requires-Dist: ipython (>=8.17.2,<9.0.0) ; extra == "dev"
Requires-Dist: matrix-nio (>=0.22.1,<0.23.0)
Requires-Dist: pytest (>=7.4.3,<8.0.0) ; extra == "dev"
Requires-Dist: pytest-asyncio (>=0.21.1,<0.22.0) ; extra == "dev"
Requires-Dist: pytest-cov (>=4.1.0,<5.0.0) ; extra == "dev"
Requires-Dist: pytest-mock (>=3.11.1,<4.0.0) ; extra == "dev"
Requires-Dist: sh (>=2.0.6,<3.0.0)
